serioushasher.py
setup.cfg
setup.py
serioushasher.egg-info/PKG-INFO
serioushasher.egg-info/SOURCES.txt
serioushasher.egg-info/dependency_links.txt
serioushasher.egg-info/entry_points.txt
serioushasher.egg-info/requires.txt
serioushasher.egg-info/top_level.txt