Metadata-Version: 1.1
Name: serioushasher
Version: 0.2
Summary: A powerful hashing tool for back-end developers
Home-page: https://github.com/junthehacker/serious_hasher
Author: Jun Zheng
Author-email: me@jackzh.com
License: UNKNOWN
Download-URL: https://github.com/junthehacker/serious_hasher/releases/tag/v0.2
Keywords: python,command-line,tool,back-end,hash,security
Platform: UNKNOWN
